jaxarc/__init__.py
jaxarc/_version.py
jaxarc/_version.pyi
jaxarc/py.typed
jaxarc/registration.py
jaxarc/state.py
jaxarc/types.py
jaxarc/conf/__init__.py
jaxarc/conf/config.yaml
jaxarc/conf/action/full.yaml
jaxarc/conf/action/raw.yaml
jaxarc/conf/action/standard.yaml
jaxarc/conf/dataset/arc_agi_1.yaml
jaxarc/conf/dataset/arc_agi_2.yaml
jaxarc/conf/dataset/concept_arc.yaml
jaxarc/conf/dataset/mini_arc.yaml
jaxarc/conf/reward/evaluation.yaml
jaxarc/conf/reward/training.yaml
jaxarc/configs/__init__.py
jaxarc/configs/action_config.py
jaxarc/configs/dataset_config.py
jaxarc/configs/environment_config.py
jaxarc/configs/grid_initialization_config.py
jaxarc/configs/logging_config.py
jaxarc/configs/main_config.py
jaxarc/configs/reward_config.py
jaxarc/configs/storage_config.py
jaxarc/configs/validation.py
jaxarc/configs/visualization_config.py
jaxarc/configs/wandb_config.py
jaxarc/envs/__init__.py
jaxarc/envs/actions.py
jaxarc/envs/environment.py
jaxarc/envs/functional.py
jaxarc/envs/grid_initialization.py
jaxarc/envs/grid_operations.py
jaxarc/envs/spaces.py
jaxarc/parsers/__init__.py
jaxarc/parsers/arc_agi.py
jaxarc/parsers/base_parser.py
jaxarc/parsers/concept_arc.py
jaxarc/parsers/mini_arc.py
jaxarc/utils/__init__.py
jaxarc/utils/buffer.py
jaxarc/utils/core.py
jaxarc/utils/dataset_manager.py
jaxarc/utils/grid_utils.py
jaxarc/utils/serialization_utils.py
jaxarc/utils/state_utils.py
jaxarc/utils/task_manager.py
jaxarc/utils/logging/__init__.py
jaxarc/utils/logging/handlers.py
jaxarc/utils/logging/logger.py
jaxarc/utils/visualization/__init__.py
jaxarc/utils/visualization/core.py
jaxarc/utils/visualization/display.py
jaxarc/utils/visualization/rl_display.py
jaxarc/wrappers/__init__.py
jaxarc/wrappers/action_wrappers.py
jaxarc/wrappers/observation_wrappers.py
jaxarc/wrappers/visualization_wrapper.py
jaxarc-1.0.2.dist-info/METADATA
jaxarc-1.0.2.dist-info/WHEEL
jaxarc-1.0.2.dist-info/licenses/LICENSE
jaxarc-1.0.2.dist-info/RECORD
