Metadata-Version: 2.4
Name: JaxARC
Version: 1.0.2
Summary: High-performance JAX-based ARC environment for RL research
Project-URL: Homepage, https://github.com/aadimator/JaxARC
Project-URL: Bug Tracker, https://github.com/aadimator/JaxARC/issues
Project-URL: Discussions, https://github.com/aadimator/JaxARC/discussions
Project-URL: Changelog, https://github.com/aadimator/JaxARC/releases
Author-email: Aadam <aadimator@gmail.com>
License-Expression: MIT
License-File: LICENSE
Classifier: Development Status :: 5 - Production/Stable
Classifier: Intended Audience :: Developers
Classifier: Intended Audience :: Science/Research
Classifier: License :: OSI Approved :: MIT License
Classifier: Operating System :: OS Independent
Classifier: Programming Language :: Python
Classifier: Programming Language :: Python :: 3
Classifier: Programming Language :: Python :: 3 :: Only
Classifier: Programming Language :: Python :: 3.9
Classifier: Programming Language :: Python :: 3.10
Classifier: Programming Language :: Python :: 3.11
Classifier: Programming Language :: Python :: 3.12
Classifier: Topic :: Scientific/Engineering
Classifier: Typing :: Typed
Requires-Python: >=3.9
Requires-Dist: cairosvg<3,>=2.8.2
Requires-Dist: drawsvg<3,>=2.4.0
Requires-Dist: equinox<0.14,>=0.13.0
Requires-Dist: hydra-core<2,>=1.3.2
Requires-Dist: jaxtyping<0.4,>=0.3.2
Requires-Dist: loguru<0.8,>=0.7.3
Requires-Dist: pyprojroot<0.4,>=0.3.0
Requires-Dist: rich<15,>=14.0.0
Requires-Dist: seaborn<0.14,>=0.13.2
Requires-Dist: stoa-env<0.2,>=0.1.2
Requires-Dist: tqdm<5,>=4.67.1
Requires-Dist: typer<0.17,>=0.16.0
